{
  "meta": {
    "sourceFile": "latest.xlsx",
    "fixedUrl": "https://creator-dashboard.rubychoustar.workers.dev",
    "generatedAt": "2026-05-25 11:31:22",
    "publishPeriod": {
      "start": "2026-05-01",
      "end": "2026-05-23",
      "label": "2026-05-01 至 2026-05-23"
    },
    "sheetNames": [
      "抖音",
      "快手"
    ],
    "accountCount": 2,
    "recordCount": 14,
    "fieldMappings": [
      "抖音：标签 -> embedStrength",
      "抖音：作品名称 -> title",
      "抖音：发布时间 -> publishAt",
      "抖音：体裁 -> genre",
      "抖音：审核状态 -> reviewStatus",
      "抖音：播放量 -> plays",
      "抖音：完播率 -> completeRate",
      "抖音：5s完播率 -> completeRate5s",
      "抖音：2s跳出率 -> bounceRate2s",
      "抖音：平均播放时长 -> avgWatchTime",
      "抖音：点赞量 -> likes",
      "抖音：分享量 -> shares",
      "抖音：评论量 -> comments",
      "抖音：收藏量 -> favorites",
      "抖音：主页访问量 -> profileVisits",
      "抖音：粉丝增量 -> followerGain",
      "抖音：投放金额 -> spend",
      "抖音：CPM -> sourceCpm",
      "抖音：CPE -> sourceCpe",
      "快手：标签 -> embedStrength",
      "快手：作品 -> title",
      "快手：发布时间 -> publishAt",
      "快手：播放量 -> plays",
      "快手：完播率 -> completeRate",
      "快手：5秒完播 -> completeRate5s",
      "快手：2秒跳出 -> bounceRate2s",
      "快手：平均播放 -> avgWatchTime",
      "快手：点赞量 -> likes",
      "快手：评论量 -> comments",
      "快手：收藏量 -> favorites",
      "快手：涨粉量 -> followerGain",
      "快手：投放金额 -> spend",
      "快手：CPM -> sourceCpm",
      "快手：CPE -> sourceCpe",
      "快手：检测到重复“完播率”列，已将后一个“完播率”作为规范字段。"
    ],
    "warnings": [],
    "matchingPolicy": {
      "enabled": false,
      "reason": "当前两平台标题与记录数不稳定，不做强制一一匹配，统一使用平台分开展示。"
    },
    "notes": [
      "趋势图按发布时间聚合，不代表逐日账号监测。",
      "CPM = spend / plays * 1000；CPE = spend / interactions。",
      "当消耗小于等于 0 时，CPM 与 CPE 统一显示为“—”。"
    ]
  },
  "normalized": {
    "accounts": [
      {
        "platform": "抖音",
        "accountName": "拍机堂大王",
        "accountLikes": 4380,
        "accountFollowers": 145
      },
      {
        "platform": "快手",
        "accountName": "拍机堂大王",
        "accountLikes": 6218,
        "accountFollowers": 813
      }
    ],
    "records": [
      {
        "id": "快手-9",
        "platform": "快手",
        "accountName": "拍机堂大王",
        "accountLikes": 6218,
        "accountFollowers": 813,
        "embedStrength": "弱植入",
        "title": "笔记本卖家？靠一波龙虾赚麻了？ #二手机 #销售新人求学之路 #拍机堂  #拜访客户",
        "publishAt": "2026-05-23T20:00:00+08:00",
        "publishDate": "2026-05-23",
        "genre": null,
        "reviewStatus": null,
        "plays": 14592,
        "completeRate": 0.076,
        "completeRate5s": 0.543,
        "bounceRate2s": 0.362,
        "avgWatchTime": 25.2,
        "likes": 2028,
        "comments": 9,
        "shares": null,
        "favorites": 17,
        "profileVisits": null,
        "followerGain": 8,
        "spend": 200,
        "sourceCpm": 13.7061403508772,
        "sourceCpe": 0.0973709834469328,
        "sourceSheet": "快手",
        "sourceRow": 9,
        "computedInteractions": 2054,
        "computedCpm": 13.70614,
        "computedCpe": 0.097371
      },
      {
        "id": "抖音-9",
        "platform": "抖音",
        "accountName": "拍机堂大王",
        "accountLikes": 4380,
        "accountFollowers": 145,
        "embedStrength": "中植入",
        "title": "会还没结束，我已经破防 #二手机回收 #销售vlog日常 #拍机堂 #二手手机 #销售新人 @抖音小助手",
        "publishAt": "2026-05-22T18:00:00+08:00",
        "publishDate": "2026-05-22",
        "genre": "1-3min视频",
        "reviewStatus": "公开",
        "plays": 26789,
        "completeRate": 0.291,
        "completeRate5s": 0.7,
        "bounceRate2s": 0.151,
        "avgWatchTime": 36.4,
        "likes": 911,
        "comments": 34,
        "shares": 4,
        "favorites": 35,
        "profileVisits": 43,
        "followerGain": 4,
        "spend": 1000,
        "sourceCpm": 37.3287543394677,
        "sourceCpe": 1.01626016260163,
        "sourceSheet": "抖音",
        "sourceRow": 9,
        "computedInteractions": 984,
        "computedCpm": 37.328754,
        "computedCpe": 1.01626
      },
      {
        "id": "快手-10",
        "platform": "快手",
        "accountName": "拍机堂大王",
        "accountLikes": 6218,
        "accountFollowers": 813,
        "embedStrength": "中植入",
        "title": "开单啦！看本王如何拿捏“黑粉”客户 #拍机堂 #二手机 #销售新人求学之路 #拜访客户",
        "publishAt": "2026-05-21T20:00:00+08:00",
        "publishDate": "2026-05-21",
        "genre": null,
        "reviewStatus": null,
        "plays": 8257,
        "completeRate": 0.03,
        "completeRate5s": 0.441,
        "bounceRate2s": 0.412,
        "avgWatchTime": 17,
        "likes": 1294,
        "comments": 4,
        "shares": null,
        "favorites": 7,
        "profileVisits": null,
        "followerGain": 14,
        "spend": 108,
        "sourceCpm": 13.0798110693957,
        "sourceCpe": 0.0827586206896552,
        "sourceSheet": "快手",
        "sourceRow": 10,
        "computedInteractions": 1305,
        "computedCpm": 13.079811,
        "computedCpe": 0.082759
      },
      {
        "id": "快手-11",
        "platform": "快手",
        "accountName": "拍机堂大王",
        "accountLikes": 6218,
        "accountFollowers": 813,
        "embedStrength": "强植入",
        "title": "销售新人遇到大佬了！一场直播卖出五六十台P40！ #二手机 #拍机堂 #销售新人求学之路 #拜访客户",
        "publishAt": "2026-05-19T20:00:00+08:00",
        "publishDate": "2026-05-19",
        "genre": null,
        "reviewStatus": null,
        "plays": 25288,
        "completeRate": 0.011,
        "completeRate5s": 0.153,
        "bounceRate2s": 0.552,
        "avgWatchTime": 5,
        "likes": 1962,
        "comments": 27,
        "shares": null,
        "favorites": 215,
        "profileVisits": null,
        "followerGain": 548,
        "spend": 492,
        "sourceCpm": 19.4558683960772,
        "sourceCpe": 0.223230490018149,
        "sourceSheet": "快手",
        "sourceRow": 11,
        "computedInteractions": 2204,
        "computedCpm": 19.455868,
        "computedCpe": 0.22323
      },
      {
        "id": "抖音-10",
        "platform": "抖音",
        "accountName": "拍机堂大王",
        "accountLikes": 4380,
        "accountFollowers": 145,
        "embedStrength": "弱植入",
        "title": "我一个新人为什么会出现在这里？ #拍机堂 #销售新人 #二手机回收 #销售vlog #二手手机 @抖音小助手",
        "publishAt": "2026-05-19T18:00:00+08:00",
        "publishDate": "2026-05-19",
        "genre": "1-3min视频",
        "reviewStatus": "公开",
        "plays": 10695,
        "completeRate": 0.086,
        "completeRate5s": 0.446,
        "bounceRate2s": 0.256,
        "avgWatchTime": 16.7,
        "likes": 428,
        "comments": 31,
        "shares": 2,
        "favorites": 8,
        "profileVisits": 119,
        "followerGain": 2,
        "spend": 500,
        "sourceCpm": 46.7508181393174,
        "sourceCpe": 1.06609808102345,
        "sourceSheet": "抖音",
        "sourceRow": 10,
        "computedInteractions": 469,
        "computedCpm": 46.750818,
        "computedCpe": 1.066098
      },
      {
        "id": "快手-12",
        "platform": "快手",
        "accountName": "拍机堂大王",
        "accountLikes": 6218,
        "accountFollowers": 813,
        "embedStrength": "中植入",
        "title": "B2B销售第二天，勇闯拍机堂招商会 #二手机回收 #拍机堂 #销售新人 #跑市场",
        "publishAt": "2026-05-17T17:30:00+08:00",
        "publishDate": "2026-05-17",
        "genre": null,
        "reviewStatus": null,
        "plays": 1712,
        "completeRate": 0.012,
        "completeRate5s": 0.361,
        "bounceRate2s": 0.325,
        "avgWatchTime": 22.8,
        "likes": 18,
        "comments": 0,
        "shares": null,
        "favorites": 0,
        "profileVisits": null,
        "followerGain": 0,
        "spend": 0,
        "sourceCpm": 0,
        "sourceCpe": 0,
        "sourceSheet": "快手",
        "sourceRow": 12,
        "computedInteractions": 18,
        "computedCpm": null,
        "computedCpe": null
      },
      {
        "id": "抖音-11",
        "platform": "抖音",
        "accountName": "拍机堂大王",
        "accountLikes": 4380,
        "accountFollowers": 145,
        "embedStrength": "强植入",
        "title": "这功能一出来，我感觉自己要疯狂开单了 #二手机批发 #销售新人 #二手手机 #拍机堂 #销售vlog @抖音小助手",
        "publishAt": "2026-05-15T18:05:10+08:00",
        "publishDate": "2026-05-15",
        "genre": "1-3min视频",
        "reviewStatus": "公开",
        "plays": 6234,
        "completeRate": 0.244,
        "completeRate5s": 0.522,
        "bounceRate2s": 0.282,
        "avgWatchTime": 24.7,
        "likes": 475,
        "comments": 23,
        "shares": 7,
        "favorites": 11,
        "profileVisits": 151,
        "followerGain": 14,
        "spend": 300,
        "sourceCpm": 48.1231953801732,
        "sourceCpe": 0.581395348837209,
        "sourceSheet": "抖音",
        "sourceRow": 11,
        "computedInteractions": 516,
        "computedCpm": 48.123195,
        "computedCpe": 0.581395
      },
      {
        "id": "快手-13",
        "platform": "快手",
        "accountName": "拍机堂大王",
        "accountLikes": 6218,
        "accountFollowers": 813,
        "embedStrength": "弱植入",
        "title": "B2B销售第一天，倒亏19.9 #二手机 #拍机堂 #销售新人 #拜访客户",
        "publishAt": "2026-05-15T17:30:00+08:00",
        "publishDate": "2026-05-15",
        "genre": null,
        "reviewStatus": null,
        "plays": 8006,
        "completeRate": 0.026,
        "completeRate5s": 0.721,
        "bounceRate2s": 0.172,
        "avgWatchTime": 26.2,
        "likes": 916,
        "comments": 12,
        "shares": null,
        "favorites": 10,
        "profileVisits": null,
        "followerGain": 3,
        "spend": 100,
        "sourceCpm": 12.4906320259805,
        "sourceCpe": 0.106609808102345,
        "sourceSheet": "快手",
        "sourceRow": 13,
        "computedInteractions": 938,
        "computedCpm": 12.490632,
        "computedCpe": 0.10661
      },
      {
        "id": "抖音-12",
        "platform": "抖音",
        "accountName": "拍机堂大王",
        "accountLikes": 4380,
        "accountFollowers": 145,
        "embedStrength": "弱植入",
        "title": "手感来了挡都挡不住哟 #二手机 #拍机堂 #销售新人 #销售vlog #二手手机批发 @抖音小助手",
        "publishAt": "2026-05-12T17:30:00+08:00",
        "publishDate": "2026-05-12",
        "genre": "1min-视频",
        "reviewStatus": "公开",
        "plays": 15498,
        "completeRate": 0.217,
        "completeRate5s": 0.504,
        "bounceRate2s": 0.294,
        "avgWatchTime": 19.6,
        "likes": 731,
        "comments": 32,
        "shares": 5,
        "favorites": 27,
        "profileVisits": 152,
        "followerGain": 10,
        "spend": 520,
        "sourceCpm": 33.5527164795457,
        "sourceCpe": 0.654088050314465,
        "sourceSheet": "抖音",
        "sourceRow": 12,
        "computedInteractions": 795,
        "computedCpm": 33.552716,
        "computedCpe": 0.654088
      },
      {
        "id": "抖音-13",
        "platform": "抖音",
        "accountName": "拍机堂大王",
        "accountLikes": 4380,
        "accountFollowers": 145,
        "embedStrength": "弱植入",
        "title": "笔记本卖家靠一波龙虾又好起来了？ #二手手机批发 #销售新人 #二手手机 #销售vlog #拍机堂 @抖音小助手",
        "publishAt": "2026-05-09T17:30:00+08:00",
        "publishDate": "2026-05-09",
        "genre": "1min-视频",
        "reviewStatus": "公开",
        "plays": 6494,
        "completeRate": 0.188,
        "completeRate5s": 0.429,
        "bounceRate2s": 0.334,
        "avgWatchTime": 15.8,
        "likes": 313,
        "comments": 14,
        "shares": 1,
        "favorites": 6,
        "profileVisits": 66,
        "followerGain": 8,
        "spend": 200,
        "sourceCpm": 30.7976593778873,
        "sourceCpe": 0.598802395209581,
        "sourceSheet": "抖音",
        "sourceRow": 13,
        "computedInteractions": 334,
        "computedCpm": 30.797659,
        "computedCpe": 0.598802
      },
      {
        "id": "抖音-14",
        "platform": "抖音",
        "accountName": "拍机堂大王",
        "accountLikes": 4380,
        "accountFollowers": 145,
        "embedStrength": "中植入",
        "title": "开单啦！看我如何拿捏“黑粉”客户 #拍机堂 #二手手机批发 #销售新人 #二手手机 #销售vlog @抖音小助手",
        "publishAt": "2026-05-07T17:30:00+08:00",
        "publishDate": "2026-05-07",
        "genre": "1-3min视频",
        "reviewStatus": "公开",
        "plays": 10296,
        "completeRate": 0.15,
        "completeRate5s": 0.605,
        "bounceRate2s": 0.206,
        "avgWatchTime": 28.7,
        "likes": 317,
        "comments": 7,
        "shares": 0,
        "favorites": 6,
        "profileVisits": 70,
        "followerGain": 3,
        "spend": 300,
        "sourceCpm": 29.1375291375291,
        "sourceCpe": 0.909090909090909,
        "sourceSheet": "抖音",
        "sourceRow": 14,
        "computedInteractions": 330,
        "computedCpm": 29.137529,
        "computedCpe": 0.909091
      },
      {
        "id": "抖音-15",
        "platform": "抖音",
        "accountName": "拍机堂大王",
        "accountLikes": 4380,
        "accountFollowers": 145,
        "embedStrength": "强植入",
        "title": "销售新人遇到大佬了！ 一场直播卖五六十台P40#二手手机批发 #销售新人 #二手手机 #销售vlog #拍机堂 @抖音小助手",
        "publishAt": "2026-05-05T17:30:00+08:00",
        "publishDate": "2026-05-05",
        "genre": "1-3min视频",
        "reviewStatus": "公开",
        "plays": 6242,
        "completeRate": 0.17,
        "completeRate5s": 0.416,
        "bounceRate2s": 0.332,
        "avgWatchTime": 19.4,
        "likes": 338,
        "comments": 10,
        "shares": 2,
        "favorites": 12,
        "profileVisits": 28,
        "followerGain": 4,
        "spend": 200,
        "sourceCpm": 32.0410124959949,
        "sourceCpe": 0.552486187845304,
        "sourceSheet": "抖音",
        "sourceRow": 15,
        "computedInteractions": 362,
        "computedCpm": 32.041012,
        "computedCpe": 0.552486
      },
      {
        "id": "抖音-16",
        "platform": "抖音",
        "accountName": "拍机堂大王",
        "accountLikes": 4380,
        "accountFollowers": 145,
        "embedStrength": "中植入",
        "title": "B2B销售第二天，勇闯拍机堂招商会 #二手手机批发 #销售新人 #二手手机 #销售vlog #拍机堂 @抖音小助手",
        "publishAt": "2026-05-03T17:30:00+08:00",
        "publishDate": "2026-05-03",
        "genre": "1-3min视频",
        "reviewStatus": "公开",
        "plays": 9206,
        "completeRate": 0.197,
        "completeRate5s": 0.52,
        "bounceRate2s": 0.292,
        "avgWatchTime": 26.9,
        "likes": 782,
        "comments": 18,
        "shares": 4,
        "favorites": 26,
        "profileVisits": 107,
        "followerGain": 10,
        "spend": 300,
        "sourceCpm": 32.5874429719748,
        "sourceCpe": 0.36144578313253,
        "sourceSheet": "抖音",
        "sourceRow": 16,
        "computedInteractions": 830,
        "computedCpm": 32.587443,
        "computedCpe": 0.361446
      },
      {
        "id": "抖音-17",
        "platform": "抖音",
        "accountName": "拍机堂大王",
        "accountLikes": 4380,
        "accountFollowers": 145,
        "embedStrength": "弱植入",
        "title": "B2B销售第一天，倒亏19.9 #二手手机批发#销售新人 #二手手机 #销售vlog  #拍机堂 @抖音小助手",
        "publishAt": "2026-05-01T17:35:33+08:00",
        "publishDate": "2026-05-01",
        "genre": "1-3min视频",
        "reviewStatus": "公开",
        "plays": 9577,
        "completeRate": 0.1,
        "completeRate5s": 0.565,
        "bounceRate2s": 0.21,
        "avgWatchTime": 24.1,
        "likes": 84,
        "comments": 21,
        "shares": 3,
        "favorites": 4,
        "profileVisits": 345,
        "followerGain": 15,
        "spend": 300,
        "sourceCpm": 31.3250495979952,
        "sourceCpe": 2.67857142857143,
        "sourceSheet": "抖音",
        "sourceRow": 17,
        "computedInteractions": 112,
        "computedCpm": 31.32505,
        "computedCpe": 2.678571
      }
    ],
    "warnings": [],
    "mappingNotes": [
      "抖音：标签 -> embedStrength",
      "抖音：作品名称 -> title",
      "抖音：发布时间 -> publishAt",
      "抖音：体裁 -> genre",
      "抖音：审核状态 -> reviewStatus",
      "抖音：播放量 -> plays",
      "抖音：完播率 -> completeRate",
      "抖音：5s完播率 -> completeRate5s",
      "抖音：2s跳出率 -> bounceRate2s",
      "抖音：平均播放时长 -> avgWatchTime",
      "抖音：点赞量 -> likes",
      "抖音：分享量 -> shares",
      "抖音：评论量 -> comments",
      "抖音：收藏量 -> favorites",
      "抖音：主页访问量 -> profileVisits",
      "抖音：粉丝增量 -> followerGain",
      "抖音：投放金额 -> spend",
      "抖音：CPM -> sourceCpm",
      "抖音：CPE -> sourceCpe",
      "快手：标签 -> embedStrength",
      "快手：作品 -> title",
      "快手：发布时间 -> publishAt",
      "快手：播放量 -> plays",
      "快手：完播率 -> completeRate",
      "快手：5秒完播 -> completeRate5s",
      "快手：2秒跳出 -> bounceRate2s",
      "快手：平均播放 -> avgWatchTime",
      "快手：点赞量 -> likes",
      "快手：评论量 -> comments",
      "快手：收藏量 -> favorites",
      "快手：涨粉量 -> followerGain",
      "快手：投放金额 -> spend",
      "快手：CPM -> sourceCpm",
      "快手：CPE -> sourceCpe",
      "快手：检测到重复“完播率”列，已将后一个“完播率”作为规范字段。"
    ]
  },
  "dashboard": {
    "overview": {
      "totalPlays": 158886,
      "totalInteractions": 11251,
      "totalFollowers": 958,
      "totalFollowerGain": 643,
      "totalSpend": 4520,
      "publishCount": 14,
      "publishCountLabel": "抖音 9 条 / 快手 5 条",
      "cpm": 28.44807,
      "cpe": 0.401742,
      "publishCountNote": "未做跨平台去重，按平台原始记录分别统计。",
      "followerNote": "粉丝总数为抖音与快手账号粉丝相加。",
      "growthNote": "净增粉基于视频级涨粉累计，不含取关口径。"
    },
    "platformComparison": [
      {
        "platform": "抖音",
        "accountName": "拍机堂大王",
        "accountFollowers": 145,
        "accountLikes": 4380,
        "publishCount": 9,
        "totalPlays": 101031,
        "avgPlays": 11225.67,
        "totalInteractions": 4732,
        "interactionRate": 0.046837,
        "followerGain": 70,
        "totalSpend": 3620,
        "avgSpend": 402.22,
        "cpm": 35.830587,
        "cpe": 0.765004,
        "interactionFormula": "点赞 + 评论 + 分享 + 收藏"
      },
      {
        "platform": "快手",
        "accountName": "拍机堂大王",
        "accountFollowers": 813,
        "accountLikes": 6218,
        "publishCount": 5,
        "totalPlays": 57855,
        "avgPlays": 11571,
        "totalInteractions": 6519,
        "interactionRate": 0.112678,
        "followerGain": 573,
        "totalSpend": 900,
        "avgSpend": 180,
        "cpm": 15.556132,
        "cpe": 0.138058,
        "interactionFormula": "点赞 + 评论 + 收藏"
      }
    ],
    "interactionDisclosures": [
      "抖音互动 = 点赞 + 评论 + 分享 + 收藏",
      "快手互动 = 点赞 + 评论 + 收藏"
    ],
    "trends": [
      {
        "date": "2026-05-01",
        "publishCount": 1,
        "plays": 9577,
        "interactions": 112,
        "followerGain": 15,
        "spend": 300,
        "cpm": 31.32505,
        "cpe": 2.678571
      },
      {
        "date": "2026-05-03",
        "publishCount": 1,
        "plays": 9206,
        "interactions": 830,
        "followerGain": 10,
        "spend": 300,
        "cpm": 32.587443,
        "cpe": 0.361446
      },
      {
        "date": "2026-05-05",
        "publishCount": 1,
        "plays": 6242,
        "interactions": 362,
        "followerGain": 4,
        "spend": 200,
        "cpm": 32.041012,
        "cpe": 0.552486
      },
      {
        "date": "2026-05-07",
        "publishCount": 1,
        "plays": 10296,
        "interactions": 330,
        "followerGain": 3,
        "spend": 300,
        "cpm": 29.137529,
        "cpe": 0.909091
      },
      {
        "date": "2026-05-09",
        "publishCount": 1,
        "plays": 6494,
        "interactions": 334,
        "followerGain": 8,
        "spend": 200,
        "cpm": 30.797659,
        "cpe": 0.598802
      },
      {
        "date": "2026-05-12",
        "publishCount": 1,
        "plays": 15498,
        "interactions": 795,
        "followerGain": 10,
        "spend": 520,
        "cpm": 33.552716,
        "cpe": 0.654088
      },
      {
        "date": "2026-05-15",
        "publishCount": 2,
        "plays": 14240,
        "interactions": 1454,
        "followerGain": 17,
        "spend": 400,
        "cpm": 28.089888,
        "cpe": 0.275103
      },
      {
        "date": "2026-05-17",
        "publishCount": 1,
        "plays": 1712,
        "interactions": 18,
        "followerGain": 0,
        "spend": 0,
        "cpm": null,
        "cpe": null
      },
      {
        "date": "2026-05-19",
        "publishCount": 2,
        "plays": 35983,
        "interactions": 2673,
        "followerGain": 550,
        "spend": 992,
        "cpm": 27.568574,
        "cpe": 0.371119
      },
      {
        "date": "2026-05-21",
        "publishCount": 1,
        "plays": 8257,
        "interactions": 1305,
        "followerGain": 14,
        "spend": 108,
        "cpm": 13.079811,
        "cpe": 0.082759
      },
      {
        "date": "2026-05-22",
        "publishCount": 1,
        "plays": 26789,
        "interactions": 984,
        "followerGain": 4,
        "spend": 1000,
        "cpm": 37.328754,
        "cpe": 1.01626
      },
      {
        "date": "2026-05-23",
        "publishCount": 1,
        "plays": 14592,
        "interactions": 2054,
        "followerGain": 8,
        "spend": 200,
        "cpm": 13.70614,
        "cpe": 0.097371
      }
    ],
    "rankings": {
      "plays": [
        {
          "id": "抖音-9",
          "platform": "抖音",
          "title": "会还没结束，我已经破防 #二手机回收 #销售vlog日常 #拍机堂 #二手手机 #销售新人 @抖音小助手",
          "publishAt": "2026-05-22T18:00:00+08:00",
          "embedStrength": "中植入",
          "plays": 26789,
          "interactions": 984,
          "followerGain": 4,
          "spend": 1000,
          "cpm": 37.328754,
          "cpe": 1.01626,
          "value": 26789
        },
        {
          "id": "快手-11",
          "platform": "快手",
          "title": "销售新人遇到大佬了！一场直播卖出五六十台P40！ #二手机 #拍机堂 #销售新人求学之路 #拜访客户",
          "publishAt": "2026-05-19T20:00:00+08:00",
          "embedStrength": "强植入",
          "plays": 25288,
          "interactions": 2204,
          "followerGain": 548,
          "spend": 492,
          "cpm": 19.455868,
          "cpe": 0.22323,
          "value": 25288
        },
        {
          "id": "抖音-12",
          "platform": "抖音",
          "title": "手感来了挡都挡不住哟 #二手机 #拍机堂 #销售新人 #销售vlog #二手手机批发 @抖音小助手",
          "publishAt": "2026-05-12T17:30:00+08:00",
          "embedStrength": "弱植入",
          "plays": 15498,
          "interactions": 795,
          "followerGain": 10,
          "spend": 520,
          "cpm": 33.552716,
          "cpe": 0.654088,
          "value": 15498
        },
        {
          "id": "快手-9",
          "platform": "快手",
          "title": "笔记本卖家？靠一波龙虾赚麻了？ #二手机 #销售新人求学之路 #拍机堂  #拜访客户",
          "publishAt": "2026-05-23T20:00:00+08:00",
          "embedStrength": "弱植入",
          "plays": 14592,
          "interactions": 2054,
          "followerGain": 8,
          "spend": 200,
          "cpm": 13.70614,
          "cpe": 0.097371,
          "value": 14592
        },
        {
          "id": "抖音-10",
          "platform": "抖音",
          "title": "我一个新人为什么会出现在这里？ #拍机堂 #销售新人 #二手机回收 #销售vlog #二手手机 @抖音小助手",
          "publishAt": "2026-05-19T18:00:00+08:00",
          "embedStrength": "弱植入",
          "plays": 10695,
          "interactions": 469,
          "followerGain": 2,
          "spend": 500,
          "cpm": 46.750818,
          "cpe": 1.066098,
          "value": 10695
        }
      ],
      "interactions": [
        {
          "id": "快手-11",
          "platform": "快手",
          "title": "销售新人遇到大佬了！一场直播卖出五六十台P40！ #二手机 #拍机堂 #销售新人求学之路 #拜访客户",
          "publishAt": "2026-05-19T20:00:00+08:00",
          "embedStrength": "强植入",
          "plays": 25288,
          "interactions": 2204,
          "followerGain": 548,
          "spend": 492,
          "cpm": 19.455868,
          "cpe": 0.22323,
          "value": 2204
        },
        {
          "id": "快手-9",
          "platform": "快手",
          "title": "笔记本卖家？靠一波龙虾赚麻了？ #二手机 #销售新人求学之路 #拍机堂  #拜访客户",
          "publishAt": "2026-05-23T20:00:00+08:00",
          "embedStrength": "弱植入",
          "plays": 14592,
          "interactions": 2054,
          "followerGain": 8,
          "spend": 200,
          "cpm": 13.70614,
          "cpe": 0.097371,
          "value": 2054
        },
        {
          "id": "快手-10",
          "platform": "快手",
          "title": "开单啦！看本王如何拿捏“黑粉”客户 #拍机堂 #二手机 #销售新人求学之路 #拜访客户",
          "publishAt": "2026-05-21T20:00:00+08:00",
          "embedStrength": "中植入",
          "plays": 8257,
          "interactions": 1305,
          "followerGain": 14,
          "spend": 108,
          "cpm": 13.079811,
          "cpe": 0.082759,
          "value": 1305
        },
        {
          "id": "抖音-9",
          "platform": "抖音",
          "title": "会还没结束，我已经破防 #二手机回收 #销售vlog日常 #拍机堂 #二手手机 #销售新人 @抖音小助手",
          "publishAt": "2026-05-22T18:00:00+08:00",
          "embedStrength": "中植入",
          "plays": 26789,
          "interactions": 984,
          "followerGain": 4,
          "spend": 1000,
          "cpm": 37.328754,
          "cpe": 1.01626,
          "value": 984
        },
        {
          "id": "快手-13",
          "platform": "快手",
          "title": "B2B销售第一天，倒亏19.9 #二手机 #拍机堂 #销售新人 #拜访客户",
          "publishAt": "2026-05-15T17:30:00+08:00",
          "embedStrength": "弱植入",
          "plays": 8006,
          "interactions": 938,
          "followerGain": 3,
          "spend": 100,
          "cpm": 12.490632,
          "cpe": 0.10661,
          "value": 938
        }
      ],
      "lowCpm": [
        {
          "id": "快手-13",
          "platform": "快手",
          "title": "B2B销售第一天，倒亏19.9 #二手机 #拍机堂 #销售新人 #拜访客户",
          "publishAt": "2026-05-15T17:30:00+08:00",
          "embedStrength": "弱植入",
          "plays": 8006,
          "interactions": 938,
          "followerGain": 3,
          "spend": 100,
          "cpm": 12.490632,
          "cpe": 0.10661,
          "value": 12.490632
        },
        {
          "id": "快手-10",
          "platform": "快手",
          "title": "开单啦！看本王如何拿捏“黑粉”客户 #拍机堂 #二手机 #销售新人求学之路 #拜访客户",
          "publishAt": "2026-05-21T20:00:00+08:00",
          "embedStrength": "中植入",
          "plays": 8257,
          "interactions": 1305,
          "followerGain": 14,
          "spend": 108,
          "cpm": 13.079811,
          "cpe": 0.082759,
          "value": 13.079811
        },
        {
          "id": "快手-9",
          "platform": "快手",
          "title": "笔记本卖家？靠一波龙虾赚麻了？ #二手机 #销售新人求学之路 #拍机堂  #拜访客户",
          "publishAt": "2026-05-23T20:00:00+08:00",
          "embedStrength": "弱植入",
          "plays": 14592,
          "interactions": 2054,
          "followerGain": 8,
          "spend": 200,
          "cpm": 13.70614,
          "cpe": 0.097371,
          "value": 13.70614
        },
        {
          "id": "快手-11",
          "platform": "快手",
          "title": "销售新人遇到大佬了！一场直播卖出五六十台P40！ #二手机 #拍机堂 #销售新人求学之路 #拜访客户",
          "publishAt": "2026-05-19T20:00:00+08:00",
          "embedStrength": "强植入",
          "plays": 25288,
          "interactions": 2204,
          "followerGain": 548,
          "spend": 492,
          "cpm": 19.455868,
          "cpe": 0.22323,
          "value": 19.455868
        },
        {
          "id": "抖音-14",
          "platform": "抖音",
          "title": "开单啦！看我如何拿捏“黑粉”客户 #拍机堂 #二手手机批发 #销售新人 #二手手机 #销售vlog @抖音小助手",
          "publishAt": "2026-05-07T17:30:00+08:00",
          "embedStrength": "中植入",
          "plays": 10296,
          "interactions": 330,
          "followerGain": 3,
          "spend": 300,
          "cpm": 29.137529,
          "cpe": 0.909091,
          "value": 29.137529
        }
      ],
      "lowCpe": [
        {
          "id": "快手-10",
          "platform": "快手",
          "title": "开单啦！看本王如何拿捏“黑粉”客户 #拍机堂 #二手机 #销售新人求学之路 #拜访客户",
          "publishAt": "2026-05-21T20:00:00+08:00",
          "embedStrength": "中植入",
          "plays": 8257,
          "interactions": 1305,
          "followerGain": 14,
          "spend": 108,
          "cpm": 13.079811,
          "cpe": 0.082759,
          "value": 0.082759
        },
        {
          "id": "快手-9",
          "platform": "快手",
          "title": "笔记本卖家？靠一波龙虾赚麻了？ #二手机 #销售新人求学之路 #拍机堂  #拜访客户",
          "publishAt": "2026-05-23T20:00:00+08:00",
          "embedStrength": "弱植入",
          "plays": 14592,
          "interactions": 2054,
          "followerGain": 8,
          "spend": 200,
          "cpm": 13.70614,
          "cpe": 0.097371,
          "value": 0.097371
        },
        {
          "id": "快手-13",
          "platform": "快手",
          "title": "B2B销售第一天，倒亏19.9 #二手机 #拍机堂 #销售新人 #拜访客户",
          "publishAt": "2026-05-15T17:30:00+08:00",
          "embedStrength": "弱植入",
          "plays": 8006,
          "interactions": 938,
          "followerGain": 3,
          "spend": 100,
          "cpm": 12.490632,
          "cpe": 0.10661,
          "value": 0.10661
        },
        {
          "id": "快手-11",
          "platform": "快手",
          "title": "销售新人遇到大佬了！一场直播卖出五六十台P40！ #二手机 #拍机堂 #销售新人求学之路 #拜访客户",
          "publishAt": "2026-05-19T20:00:00+08:00",
          "embedStrength": "强植入",
          "plays": 25288,
          "interactions": 2204,
          "followerGain": 548,
          "spend": 492,
          "cpm": 19.455868,
          "cpe": 0.22323,
          "value": 0.22323
        },
        {
          "id": "抖音-16",
          "platform": "抖音",
          "title": "B2B销售第二天，勇闯拍机堂招商会 #二手手机批发 #销售新人 #二手手机 #销售vlog #拍机堂 @抖音小助手",
          "publishAt": "2026-05-03T17:30:00+08:00",
          "embedStrength": "中植入",
          "plays": 9206,
          "interactions": 830,
          "followerGain": 10,
          "spend": 300,
          "cpm": 32.587443,
          "cpe": 0.361446,
          "value": 0.361446
        }
      ]
    },
    "embedAnalysis": [
      {
        "embedStrength": "弱植入",
        "videoCount": 6,
        "avgPlays": 10810.33,
        "avgInteractions": 783.67,
        "avgFollowerGain": 7.67,
        "avgSpend": 303.33,
        "avgCpm": 28.103836,
        "avgCpe": 0.866923
      },
      {
        "embedStrength": "中植入",
        "videoCount": 5,
        "avgPlays": 11252,
        "avgInteractions": 693.4,
        "avgFollowerGain": 6.2,
        "avgSpend": 341.6,
        "avgCpm": 28.033384,
        "avgCpe": 0.592389
      },
      {
        "embedStrength": "强植入",
        "videoCount": 3,
        "avgPlays": 12588,
        "avgInteractions": 1027.33,
        "avgFollowerGain": 188.67,
        "avgSpend": 330.67,
        "avgCpm": 33.206692,
        "avgCpe": 0.45237
      }
    ],
    "contentTable": [
      {
        "id": "快手-9",
        "platform": "快手",
        "publishAt": "2026-05-23T20:00:00+08:00",
        "title": "笔记本卖家？靠一波龙虾赚麻了？ #二手机 #销售新人求学之路 #拍机堂  #拜访客户",
        "embedStrength": "弱植入",
        "plays": 14592,
        "interactions": 2054,
        "followerGain": 8,
        "spend": 200,
        "cpm": 13.70614,
        "cpe": 0.097371
      },
      {
        "id": "抖音-9",
        "platform": "抖音",
        "publishAt": "2026-05-22T18:00:00+08:00",
        "title": "会还没结束，我已经破防 #二手机回收 #销售vlog日常 #拍机堂 #二手手机 #销售新人 @抖音小助手",
        "embedStrength": "中植入",
        "plays": 26789,
        "interactions": 984,
        "followerGain": 4,
        "spend": 1000,
        "cpm": 37.328754,
        "cpe": 1.01626
      },
      {
        "id": "快手-10",
        "platform": "快手",
        "publishAt": "2026-05-21T20:00:00+08:00",
        "title": "开单啦！看本王如何拿捏“黑粉”客户 #拍机堂 #二手机 #销售新人求学之路 #拜访客户",
        "embedStrength": "中植入",
        "plays": 8257,
        "interactions": 1305,
        "followerGain": 14,
        "spend": 108,
        "cpm": 13.079811,
        "cpe": 0.082759
      },
      {
        "id": "快手-11",
        "platform": "快手",
        "publishAt": "2026-05-19T20:00:00+08:00",
        "title": "销售新人遇到大佬了！一场直播卖出五六十台P40！ #二手机 #拍机堂 #销售新人求学之路 #拜访客户",
        "embedStrength": "强植入",
        "plays": 25288,
        "interactions": 2204,
        "followerGain": 548,
        "spend": 492,
        "cpm": 19.455868,
        "cpe": 0.22323
      },
      {
        "id": "抖音-10",
        "platform": "抖音",
        "publishAt": "2026-05-19T18:00:00+08:00",
        "title": "我一个新人为什么会出现在这里？ #拍机堂 #销售新人 #二手机回收 #销售vlog #二手手机 @抖音小助手",
        "embedStrength": "弱植入",
        "plays": 10695,
        "interactions": 469,
        "followerGain": 2,
        "spend": 500,
        "cpm": 46.750818,
        "cpe": 1.066098
      },
      {
        "id": "快手-12",
        "platform": "快手",
        "publishAt": "2026-05-17T17:30:00+08:00",
        "title": "B2B销售第二天，勇闯拍机堂招商会 #二手机回收 #拍机堂 #销售新人 #跑市场",
        "embedStrength": "中植入",
        "plays": 1712,
        "interactions": 18,
        "followerGain": 0,
        "spend": 0,
        "cpm": null,
        "cpe": null
      },
      {
        "id": "抖音-11",
        "platform": "抖音",
        "publishAt": "2026-05-15T18:05:10+08:00",
        "title": "这功能一出来，我感觉自己要疯狂开单了 #二手机批发 #销售新人 #二手手机 #拍机堂 #销售vlog @抖音小助手",
        "embedStrength": "强植入",
        "plays": 6234,
        "interactions": 516,
        "followerGain": 14,
        "spend": 300,
        "cpm": 48.123195,
        "cpe": 0.581395
      },
      {
        "id": "快手-13",
        "platform": "快手",
        "publishAt": "2026-05-15T17:30:00+08:00",
        "title": "B2B销售第一天，倒亏19.9 #二手机 #拍机堂 #销售新人 #拜访客户",
        "embedStrength": "弱植入",
        "plays": 8006,
        "interactions": 938,
        "followerGain": 3,
        "spend": 100,
        "cpm": 12.490632,
        "cpe": 0.10661
      },
      {
        "id": "抖音-12",
        "platform": "抖音",
        "publishAt": "2026-05-12T17:30:00+08:00",
        "title": "手感来了挡都挡不住哟 #二手机 #拍机堂 #销售新人 #销售vlog #二手手机批发 @抖音小助手",
        "embedStrength": "弱植入",
        "plays": 15498,
        "interactions": 795,
        "followerGain": 10,
        "spend": 520,
        "cpm": 33.552716,
        "cpe": 0.654088
      },
      {
        "id": "抖音-13",
        "platform": "抖音",
        "publishAt": "2026-05-09T17:30:00+08:00",
        "title": "笔记本卖家靠一波龙虾又好起来了？ #二手手机批发 #销售新人 #二手手机 #销售vlog #拍机堂 @抖音小助手",
        "embedStrength": "弱植入",
        "plays": 6494,
        "interactions": 334,
        "followerGain": 8,
        "spend": 200,
        "cpm": 30.797659,
        "cpe": 0.598802
      },
      {
        "id": "抖音-14",
        "platform": "抖音",
        "publishAt": "2026-05-07T17:30:00+08:00",
        "title": "开单啦！看我如何拿捏“黑粉”客户 #拍机堂 #二手手机批发 #销售新人 #二手手机 #销售vlog @抖音小助手",
        "embedStrength": "中植入",
        "plays": 10296,
        "interactions": 330,
        "followerGain": 3,
        "spend": 300,
        "cpm": 29.137529,
        "cpe": 0.909091
      },
      {
        "id": "抖音-15",
        "platform": "抖音",
        "publishAt": "2026-05-05T17:30:00+08:00",
        "title": "销售新人遇到大佬了！ 一场直播卖五六十台P40#二手手机批发 #销售新人 #二手手机 #销售vlog #拍机堂 @抖音小助手",
        "embedStrength": "强植入",
        "plays": 6242,
        "interactions": 362,
        "followerGain": 4,
        "spend": 200,
        "cpm": 32.041012,
        "cpe": 0.552486
      },
      {
        "id": "抖音-16",
        "platform": "抖音",
        "publishAt": "2026-05-03T17:30:00+08:00",
        "title": "B2B销售第二天，勇闯拍机堂招商会 #二手手机批发 #销售新人 #二手手机 #销售vlog #拍机堂 @抖音小助手",
        "embedStrength": "中植入",
        "plays": 9206,
        "interactions": 830,
        "followerGain": 10,
        "spend": 300,
        "cpm": 32.587443,
        "cpe": 0.361446
      },
      {
        "id": "抖音-17",
        "platform": "抖音",
        "publishAt": "2026-05-01T17:35:33+08:00",
        "title": "B2B销售第一天，倒亏19.9 #二手手机批发#销售新人 #二手手机 #销售vlog  #拍机堂 @抖音小助手",
        "embedStrength": "弱植入",
        "plays": 9577,
        "interactions": 112,
        "followerGain": 15,
        "spend": 300,
        "cpm": 31.32505,
        "cpe": 2.678571
      }
    ],
    "matchingPolicy": {
      "enabled": false,
      "reason": "当前两平台标题与记录数不稳定，不做强制一一匹配，统一使用平台分开展示。"
    },
    "insights": [
      "快手本周期同时拿到更优效率与更高单条曝光，是当前更稳的主阵地。",
      "强植入内容在当前样本里更平衡，兼顾互动与投流效率，适合作为下一轮复用方向。",
      "当前趋势只适合按发布时间聚合复盘；其中快手互动率为 11.3%，更适合继续验证选题与表达模板。"
    ]
  }
}
